savvy/__init__.py
savvy/shell.py
savvy/internal/__init__.py
savvy/internal/fallback_logger.py
savvy-0.0.1.dist-info/METADATA
savvy-0.0.1.dist-info/RECORD
savvy-0.0.1.dist-info/WHEEL
savvy-0.0.1.dist-info/top_level.txt
