Metadata-Version: 2.1
Name: savvy
Version: 0.0.1
Summary: Consolidated assortment of utility modules & classes for savvy Python development.
Home-page: https://github.com/whittlbc/savvy
Author: Ben Whittle
Author-email: benwhittle31@gmail.com
License: MIT
Platform: UNKNOWN
